{
    "fluentMethods": true,
    "relationships": [
        {
            "relationshipType": "one-to-many",
            "relationshipName": "product",
            "otherEntityName": "product",
            "otherEntityRelationshipName": "supplier"
        }
    ],
    "fields": [
        {
            "fieldName": "name",
            "fieldType": "String"
        },
        {
            "fieldName": "contry",
            "fieldType": "String"
        },
        {
            "fieldName": "email",
            "fieldType": "String"
        },
        {
            "fieldName": "phone",
            "fieldType": "String"
        },
        {
            "fieldName": "site",
            "fieldType": "String"
        },
        {
            "fieldName": "datePurchase",
            "fieldType": "Instant"
        },
        {
            "fieldName": "contact",
            "fieldType": "String"
        }
    ],
    "changelogDate": "20180912213417",
    "entityTableName": "supplier",
    "dto": "no",
    "pagination": "no",
    "service": "no",
    "jpaMetamodelFiltering": false
}